volcano/poller/__init__.py
volcano/poller/__main__.py
volcano/poller/base_ctx.py
volcano/poller/base_dev.py
volcano/poller/base_prot.py
volcano/poller/build_cfg.py
volcano/poller/channel_base.py
volcano/poller/channel_serial.py
volcano/poller/channel_tcp.py
volcano/poller/connected_values.py
volcano/poller/mb_ctx.py
volcano/poller/mb_dev.py
volcano/poller/mb_frame.py
volcano/poller/mb_prot.py
volcano/poller/merk_ctx.py
volcano/poller/merk_defs.py
volcano/poller/merk_dev.py
volcano/poller/merk_nzif_common.py
volcano/poller/merk_nzif_ctx.py
volcano/poller/merk_prot.py
volcano/poller/modbus_protocol_client.py
volcano/poller/moxa_di_prot.py
volcano/poller/num_ops.py
volcano/poller/nzif.json
volcano/poller/nzif_ctx.py
volcano/poller/nzif_defs.py
volcano/poller/nzif_dev.py
volcano/poller/nzif_profiles.py
volcano/poller/nzif_prot.py
volcano/poller/time_tools.py
volcano/poller/tools.py
volcano_poller-1.4.3.dist-info/LICENSE
volcano_poller-1.4.3.dist-info/METADATA
volcano_poller-1.4.3.dist-info/WHEEL
volcano_poller-1.4.3.dist-info/top_level.txt
volcano_poller-1.4.3.dist-info/RECORD
